{"gnp per capita":["HNP na hlavu"],"god knows where":["bůhvíkde"],"god knows who":["bůhvíkdo"],"green data book":["Zelená kniha"],"green lights programme.":["program Zelená světla"],"gross national product":["hrubý národní produkt"],"geological dam cross-section":["hrázový profil"],"get a lift":["svézt se"],"get a lift/ride":["svézt se"],"get a suntan":["opalovat se","opálit se"],"get acquainted with":["seznamovat se","seznámit se"],"get ahead of":["dostat se před (někoho)","před"],"get along with":["vycházet s"],"get around to":["vrátit se"],"get away with":["mít úspěch s"],"get carried away":["dát se unést"],"get down to":["pustit se do","dostat se k","dát se do"],"get his prints":["sejmi jeho otisky"],"get hold of":["zmocnit se","chopit se"],"get in touch":["ozvat se"],"get into trouble":["mít nepříjemnost","dostat se do nesnází"],"get it on":["souložit"],"get on well":["dařit se"],"get on with":["snášet se s"],"get one's lumps":["dostat co proto"],"get out of":["zbavit se","vyplést se","vymotat se","vymknout se","vyvléknout se z","vyplést se z","vymotat se z"],"get rid of":["zbavovat se","zbavit se"],"get the goods":["dělat, co se čeká"],"get through with":["dokončit"],"get to it":["jít na věc"],"get to know":["poznávat","seznámit se","poznat"],"get up to":["dosáhnout na"],"get wind of":["zvětřit"],"give a message":["vyřídit"],"give and take":["kompromis","vzájemné ústupky","kompromisy"],"give birth to":["rodit","porodit"],"give change for":["rozměnit"],"give oneself up":["oddat se"],"give the eye":["podívat se na"],"give the gate":["dát košem"],"give the sack":["dát padáka"],"give up on":["vykašlat se na"],"give way to":["propadat"],"give what for":["dát co proto"],"global environmental facility":["globální environmentální vybavenost"],"go along with":["souhlasit s"],"go and see":["jít navštívit"],"go back on":["vycouvat","nechat na holičkách"],"go for broke":["jít pro změnu"],"go off into":["zajíždět","zajet"],"go one better":["přetrumfnout","překonat"],"go out with":["mít známost s","jít ven s","chodit s"],"go separate ways":["rozejít se"],"go to bed":["jít spát","jít do postele"],"go to pieces":["zhroutit se","roztříštit se","rozsypat se","rozbít se"],"go to pot":["natáhnout brka"],"go to sleep":["usnout"],"go too far":["zacházet do krajnosti"],"government intervention failure":["selhání intervencí vlády"],"government transfer payments":["vládní transferové platby"],"grace of god":["boží milosrdenství"],"grape press plant":["lisovna na víno"],"grassed depression strip":["úlehový zatravněný pás"],"gravitation water accumulation":["zvodeň"],"gross domestic product":["HDP","hrubý domácí produkt","hrubý národní produkt"],"gross primary production":["celková primární produkce (limnologie)"],"gross production rate":["celkový produkční výkon (limnologie)"],"ground water catchment":["povodí podzemní vody"],"groundwater table depth":["hloubka hladiny podzemní vody"],"grow into one":["srůst"],"guard of honor":["čestná stráž"],"guest of honour":["čestný host"],"gross profit margin":["hrubé ziskové rozpětí"],"great white shark":["bílý žralok"],"grain of shot":["brok"],"give a ring":["zatelefonovat"],"gaseous radioactive waste":["plynný radioaktivní odpad"]}